sma_manager_api/SMA.py
sma_manager_api/__init__.py
sma_manager-2.1.0.dist-info/LICENSE
sma_manager-2.1.0.dist-info/METADATA
sma_manager-2.1.0.dist-info/WHEEL
sma_manager-2.1.0.dist-info/top_level.txt
sma_manager-2.1.0.dist-info/RECORD
